pycotem/__init__.py
pycotem/crystal/__init__.py
pycotem/crystal/__main__.py
pycotem/crystal/bcc.txt
pycotem/crystal/cfc.txt
pycotem/crystal/crystal-icon.png
pycotem/crystal/crystalUI.py
pycotem/crystal/crystalUI.ui
pycotem/crystal/hcp.txt
pycotem/crystal/l10.txt
pycotem/crystal/space_group.txt
pycotem/crystal/structure.txt
pycotem/diffraction/__init__.py
pycotem/diffraction/__main__.py
pycotem/diffraction/calibrations.txt
pycotem/diffraction/diffraction-icon.png
pycotem/diffraction/diffractionUI.py
pycotem/diffraction/diffractionUI.ui
pycotem/diffraction/import_export_exemple.txt
pycotem/diffraction/scattering.txt
pycotem/diffraction/space_group.txt
pycotem/diffraction/structure.txt
pycotem/interface/DrawInterfaceUI.py
pycotem/interface/DrawInterfaceUI.ui
pycotem/interface/DrawStretchedUI.py
pycotem/interface/DrawStretchedUI.ui
pycotem/interface/__init__.py
pycotem/interface/__main__.py
pycotem/interface/draw_stretched.ui
pycotem/interface/import_export_exemple_direction.txt
pycotem/interface/import_export_exemple_plane.txt
pycotem/interface/interface-icon.png
pycotem/interface/interfaceUI.py
pycotem/interface/interfaceUI.ui
pycotem/interface/microscope.txt
pycotem/interface/structure.txt
pycotem/kikuchi/__init__.py
pycotem/kikuchi/__main__.py
pycotem/kikuchi/calibrations.txt
pycotem/kikuchi/kikuchi-icon.png
pycotem/kikuchi/kikuchiUI.py
pycotem/kikuchi/kikuchiUI.ui
pycotem/kikuchi/refineUI.py
pycotem/kikuchi/refineUI.ui
pycotem/kikuchi/scattering.txt
pycotem/kikuchi/space_group.txt
pycotem/kikuchi/structure.txt
pycotem/kikuchi/tiltUI.py
pycotem/kikuchi/tiltUI.ui
pycotem/misorientation/__init__.py
pycotem/misorientation/__main__.py
pycotem/misorientation/misorientation-icon.png
pycotem/misorientation/misorientationUI.py
pycotem/misorientation/misorientationUI.ui
pycotem/misorientation/stereo.png
pycotem/misorientation/structure.txt
pycotem/stereoproj/__init__.py
pycotem/stereoproj/__main__.py
pycotem/stereoproj/angleUI.py
pycotem/stereoproj/angleUI.ui
pycotem-2.13.0.dist-info/licenses/LICENSE
pycotem-2.13.0.dist-info/METADATA
pycotem-2.13.0.dist-info/WHEEL
pycotem-2.13.0.dist-info/top_level.txt
pycotem-2.13.0.dist-info/RECORD
