Metadata-Version: 2.4
Name: pycotem
Version: 2.13.0
Summary: A python package for working with crystal orientations in transmission electron microscopy
Home-page: https://mompiou.github.io/pycotem/
Download-URL: https://github.com/mompiou/pycotem
Author: f. mompiou
Author-email: frederic.mompiou@cemes.fr
License: GPL-3.0
Keywords: scientific,crystallography,electron microscopy
Classifier: Intended Audience :: Science/Research
Classifier: Programming Language :: Python :: 3
License-File: LICENSE
Dynamic: author
Dynamic: author-email
Dynamic: classifier
Dynamic: description
Dynamic: description-content-type
Dynamic: download-url
Dynamic: home-page
Dynamic: keywords
Dynamic: license
Dynamic: license-file
Dynamic: summary
